<annotation>
	<folder>sealsatble</folder>
	<filename>IMG_1829.jpg</filename>
	<path>C:\Users\MENDE MUKESH\Desktop\dataset\sealsatble\IMG_1829.jpg</path>
	<source>
		<database>Unknown</database>
	</source>
	<size>
		<width>3024</width>
		<height>4032</height>
		<depth>3</depth>
	</size>
	<segmented>0</segmented>
	<object>
		<name>sealstable</name>
		<pose>Unspecified</pose>
		<truncated>0</truncated>
		<difficult>0</difficult>
		<bndbox>
			<xmin>366</xmin>
			<ymin>315</ymin>
			<xmax>1370</xmax>
			<ymax>1359</ymax>
		</bndbox>
	</object>
</annotation>
